core_aws_cdk/__init__.py
core_aws_cdk/py.typed
core_aws_cdk/stacks/__init__.py
core_aws_cdk/stacks/base.py
core_aws_cdk/stacks/network.py
core_aws_cdk/stacks/s3.py
core_aws_cdk/stacks/sns.py
core_aws_cdk/stacks/sqs.py
core_aws_cdk/stacks/lambdas/__init__.py
core_aws_cdk/stacks/lambdas/assets.py
core_aws_cdk/stacks/lambdas/base.py
core_aws_cdk-2.0.0.dist-info/licenses/LICENSE
core_aws_cdk-2.0.0.dist-info/METADATA
core_aws_cdk-2.0.0.dist-info/WHEEL
core_aws_cdk-2.0.0.dist-info/top_level.txt
core_aws_cdk-2.0.0.dist-info/RECORD
