Metadata-Version: 2.4
Name: core-aws-cdk
Version: 2.0.0
Summary: This project contains the commons elements to create infrastructure in AWS using AWS CDK...
Author-email: Alejandro Cora González <alek.cora.glez@gmail.com>
Maintainer: Alejandro Cora González
License-Expression: MIT
Project-URL: Homepage, https://gitlab.com/bytecode-solutions/infrastructure/core-aws-cdk
Project-URL: Repository, https://gitlab.com/bytecode-solutions/core/core-aws-cdk
Project-URL: Documentation, https://core-aws-cdk.readthedocs.io/en/latest/
Project-URL: Issues, https://gitlab.com/bytecode-solutions/core/core-aws-cdk/-/issues
Project-URL: Changelog, https://gitlab.com/bytecode-solutions/core/core-aws-cdk/-/blob/master/CHANGELOG.md
Classifier: Intended Audience :: Developers
Classifier: Development Status :: 5 - Production/Stable
Classifier: Topic :: Software Development :: Libraries :: Python Modules
Classifier: Topic :: Utilities
Classifier: Programming Language :: Python :: 3
Classifier: Programming Language :: Python :: 3 :: Only
Classifier: Programming Language :: Python :: 3.9
Classifier: Programming Language :: Python :: 3.10
Classifier: Programming Language :: Python :: 3.11
Classifier: Programming Language :: Python :: 3.12
Classifier: Programming Language :: Python :: 3.13
Requires-Python: >=3.9
License-File: LICENSE
Requires-Dist: aws-cdk-lib>=2.195.0
Requires-Dist: core-mixins>=2.1.0
Provides-Extra: dev
Requires-Dist: core-dev-tools>=1.0.1; extra == "dev"
Requires-Dist: core-tests>=2.0.3; extra == "dev"
Requires-Dist: pytest-xdist>=3.5.0; extra == "dev"
Dynamic: license-file
